sec_summary_llm/__init__.py
sec_summary_llm/main.py
sec_summary_llm/prompts.py
sec_summary_llm-2025.12.21193952.dist-info/METADATA
sec_summary_llm-2025.12.21193952.dist-info/WHEEL
sec_summary_llm-2025.12.21193952.dist-info/top_level.txt
sec_summary_llm-2025.12.21193952.dist-info/RECORD
