Metadata-Version: 2.4
Name: sec-summary-llm
Version: 2025.12.21193952
Summary: packages extracts structured summaries from security and government texts using LLM
Author-email: sec-summary-llm <hi@eugene.plus>
License: MIT
Project-URL: Homepage, https://github.com/chigwell/sec-summary-llm
Requires-Python: >=3.9
Requires-Dist: langchain-llm7>=0.0.0
Requires-Dist: llmatch-messages>=0.0.0
Requires-Dist: langchain-core>=0.3.0
